voedl.py
voedl-0.2.5.3.dist-info/METADATA
voedl-0.2.5.3.dist-info/WHEEL
voedl-0.2.5.3.dist-info/entry_points.txt
voedl-0.2.5.3.dist-info/top_level.txt
voedl-0.2.5.3.dist-info/RECORD
