Metadata-Version: 2.4
Name: voedl
Version: 0.2.5.3
Summary: Bulk VOE.sx video downloader with resolver and aria2 support
Home-page: https://github.com/M2tecDev/voedl
Author: M2tecDev
License: MIT
Keywords: voe downloader,voe.sx,mp4,aria2c,yt-dlp,cli
Classifier: Programming Language :: Python :: 3
Classifier: License :: OSI Approved :: MIT License
Classifier: Operating System :: OS Independent
Requires-Dist: requests
Requires-Dist: yt-dlp
Requires-Dist: beautifulsoup4
Requires-Dist: tqdm
